game_lingo/__init__.py
game_lingo/__main__.py
game_lingo/apis/__init__.py
game_lingo/apis/deepl_api.py
game_lingo/apis/google_translate_api.py
game_lingo/apis/rawg_api.py
game_lingo/apis/steam_api.py
game_lingo/cli.py
game_lingo/config.py
game_lingo/core/__init__.py
game_lingo/core/cache.py
game_lingo/core/rate_limiter.py
game_lingo/core/translator.py
game_lingo/exceptions.py
game_lingo/models/__init__.py
game_lingo/models/api_response.py
game_lingo/models/game.py
game_lingo/models/game_info.py
game_lingo-0.4.1.dist-info/entry_points.txt
game_lingo-0.4.1.dist-info/licenses/LICENSE
game_lingo-0.4.1.dist-info/METADATA
game_lingo-0.4.1.dist-info/WHEEL
game_lingo-0.4.1.dist-info/RECORD
