Metadata-Version: 2.4
Name: game-lingo
Version: 0.4.1
Summary: Multi-language video game description translator with smart API orchestration
License: MIT
License-File: LICENSE
Keywords: games,translation,steam,rawg,deepl,videogames,api,multilingual,i18n,localization
Author: Sermodi
Author-email: sermodsoftware@gmail.com
Requires-Python: >=3.9,<4.0
Classifier: Development Status :: 3 - Alpha
Classifier: Intended Audience :: Developers
Classifier: License :: OSI Approved :: MIT License
Classifier: Operating System :: OS Independent
Classifier: Programming Language :: Python :: 3
Classifier: Programming Language :: Python :: 3.9
Classifier: Programming Language :: Python :: 3.10
Classifier: Programming Language :: Python :: 3.11
Classifier: Programming Language :: Python :: 3.12
Classifier: Programming Language :: Python :: 3.13
Classifier: Programming Language :: Python :: 3.14
Classifier: Topic :: Games/Entertainment
Classifier: Topic :: Software Development :: Libraries :: Python Modules
Requires-Dist: aiohttp (>=3.9.0,<4.0.0)
Requires-Dist: asyncio (>=3.4.3,<4.0.0)
Requires-Dist: pydantic (>=2.5.0,<3.0.0)
Requires-Dist: python-decouple (>=3.8,<4.0)
Requires-Dist: requests (>=2.31.0,<3.0.0)
Requires-Dist: tenacity (>=8.2.3,<9.0.0)
Requires-Dist: tomli (>=2.0.0,<3.0.0) ; python_version < "3.11"
Project-URL: Homepage, https://github.com/Sermodi/game-lingo
Project-URL: Repository, https://github.com/Sermodi/game-lingo
